omuplugin_obssync/__init__.py
omuplugin_obssync/__main__.py
omuplugin_obssync/obsconfig.py
omuplugin_obssync/plugin.py
omuplugin_obssync/version.py
omuplugin_obssync/script/.gitignore
omuplugin_obssync/script/find_venv.py
omuplugin_obssync/script/omuapps_plugin.py
omuplugin_obssync-0.6.12.dist-info/METADATA
omuplugin_obssync-0.6.12.dist-info/WHEEL
omuplugin_obssync-0.6.12.dist-info/entry_points.txt
omuplugin_obssync-0.6.12.dist-info/RECORD
