Metadata-Version: 2.3
Name: omuplugin_obssync
Version: 0.6.12
Summary: Add your description here
Author-email: am230 <111672334+am230@users.noreply.github.com>
Requires-Python: >=3.12
Requires-Dist: loguru>=0.7.2
Requires-Dist: omu-chat>=0.1.9
Requires-Dist: psutil>=5.9.8
